<!DOCTYPE suite SYSTEM "http://testng.org/testng-1.0.dtd" >
<suite name="Cyberiansoft VNext client tests" verbose="10" configfailurepolicy="continue">
    <listeners>
        <listener class-name="com.cyberiansoft.test.vnext.listeners.TestServiceListener"/>
    </listeners>
    <parameter name="bo.url" value="https://manheim-reconpro-uat.cyberianconcepts.com"  />
    <parameter name="lic.name" value="IntegrationTests"  />
    <test name="Tests for VNext client" group-by-instances="true">
        <classes>
            <class name="com.cyberiansoft.test.manheimintegration.testcases.FindWorkOrdersTestCase">
            </class>
        </classes>
    </test>
</suite>